[
    {
        "key": "dbln",
        "value": "%7B%22100092097525893%22%3A%22tWaY3x9w%22%2C%2261552191486868%22%3A%22nIHBCk3a%22%2C%2261566852036572%22%3A%22ewiGmCiz%22%7D",
        "domain": "facebook.com",
        "path": "/login/device-based/",
        "hostOnly": false,
        "creation": "2024-10-11T23:21:54.609Z",
        "lastAccessed": "2024-10-11T23:21:54.609Z"
    },
    {
        "key": "datr",
        "value": "MXcFZ_28CJ8O2kiugEohAhYn",
        "domain": "facebook.com",
        "path": "/",
        "hostOnly": false,
        "creation": "2024-10-11T23:21:54.609Z",
        "lastAccessed": "2024-10-11T23:21:54.609Z"
    },
    {
        "key": "sb",
        "value": "MXcFZ_0dVlJb3Q0-0d4ZwZuw",
        "domain": "facebook.com",
        "path": "/",
        "hostOnly": false,
        "creation": "2024-10-11T23:21:54.609Z",
        "lastAccessed": "2024-10-11T23:21:54.609Z"
    },
    {
        "key": "vpd",
        "value": "v1%3B842x424x1.445365309715271",
        "domain": "facebook.com",
        "path": "/",
        "hostOnly": false,
        "creation": "2024-10-11T23:21:54.609Z",
        "lastAccessed": "2024-10-11T23:21:54.609Z"
    },
    {
        "key": "ps_l",
        "value": "1",
        "domain": "facebook.com",
        "path": "/",
        "hostOnly": false,
        "creation": "2024-10-11T23:21:54.609Z",
        "lastAccessed": "2024-10-11T23:21:54.609Z"
    },
    {
        "key": "ps_n",
        "value": "1",
        "domain": "facebook.com",
        "path": "/",
        "hostOnly": false,
        "creation": "2024-10-11T23:21:54.609Z",
        "lastAccessed": "2024-10-11T23:21:54.609Z"
    },
    {
        "key": "m_pixel_ratio",
        "value": "1.445365309715271",
        "domain": "facebook.com",
        "path": "/",
        "hostOnly": false,
        "creation": "2024-10-11T23:21:54.609Z",
        "lastAccessed": "2024-10-11T23:21:54.609Z"
    },
    {
        "key": "locale",
        "value": "bn_IN",
        "domain": "facebook.com",
        "path": "/",
        "hostOnly": false,
        "creation": "2024-10-11T23:21:54.609Z",
        "lastAccessed": "2024-10-11T23:21:54.609Z"
    },
    {
        "key": "c_user",
        "value": "61552191486868",
        "domain": "facebook.com",
        "path": "/",
        "hostOnly": false,
        "creation": "2024-10-11T23:21:54.609Z",
        "lastAccessed": "2024-10-11T23:21:54.609Z"
    },
    {
        "key": "fr",
        "value": "0Q8HS3TEq4CmAR6DC.AWXPlXeX4VmjK55_-NqYaQ9wJjg.BnBXcx..AAA.0.0.BnCbME.AWVO1egiRDE",
        "domain": "facebook.com",
        "path": "/",
        "hostOnly": false,
        "creation": "2024-10-11T23:21:54.609Z",
        "lastAccessed": "2024-10-11T23:21:54.609Z"
    },
    {
        "key": "xs",
        "value": "29%3AQi8Tz1UL9vvX3g%3A2%3A1728688900%3A-1%3A5170",
        "domain": "facebook.com",
        "path": "/",
        "hostOnly": false,
        "creation": "2024-10-11T23:21:54.609Z",
        "lastAccessed": "2024-10-11T23:21:54.609Z"
    },
    {
        "key": "wd",
        "value": "424x942",
        "domain": "facebook.com",
        "path": "/",
        "hostOnly": false,
        "creation": "2024-10-11T23:21:54.609Z",
        "lastAccessed": "2024-10-11T23:21:54.609Z"
    },
    {
        "key": "fbl_st",
        "value": "101424224%3BT%3A28811481",
        "domain": "facebook.com",
        "path": "/",
        "hostOnly": false,
        "creation": "2024-10-11T23:21:54.609Z",
        "lastAccessed": "2024-10-11T23:21:54.609Z"
    },
    {
        "key": "wl_cbv",
        "value": "v2%3Bclient_version%3A2645%3Btimestamp%3A1728688907",
        "domain": "facebook.com",
        "path": "/",
        "hostOnly": false,
        "creation": "2024-10-11T23:21:54.609Z",
        "lastAccessed": "2024-10-11T23:21:54.609Z"
    }
]
